{"metadata":{"iso_language_code":"en"},"user":{"screen_name":"antivirusbb","id_str":"544789168","id":544789168},"entities":{"user_mentions":[],"hashtags":[],"urls":[{"url":"http://t.co/CVb5w1z3","display_url":"bit.ly/K3UCTz","indices":[116,136],"expanded_url":"http://bit.ly/K3UCTz"}]},"coordinates":null,"text":"AVG Anti-Virus Free Edition 2012 review - PC Advisor: AVG Anti-Virus Free Edition 2012 reviewPC AdvisorBy Simon ... http://t.co/CVb5w1z3","created_at":"Thu, 03 May 2012 16:24:43 +0000","id_str":"198085691954053122","id":198085691954053120}
{"metadata":{"iso_language_code":"en"},"user":{"screen_name":"Babanhajiya","id_str":"128992019","id":128992019},"entities":{"user_mentions":[{"id_str":"473923125","screen_name":"yusufmdz","indices":[3,12],"name":"M.d Yusuf","id":473923125},{"id_str":"22059388","screen_name":"elrufai","indices":[14,22],"name":"Nasir El-Rufai","id":22059388}],"hashtags":[],"urls":[]},"coordinates":null,"text":"RT @yusufmdz: @elrufai Gun men attack BUK in broad daylight nd still managed to escape?Pl let's reflect;this is beyond security lapse,it is complicity.","created_at":"Sun, 29 Apr 2012 15:02:17 +0000","id_str":"196615395648618496","id":196615395648618500}
{"metadata":{"iso_language_code":"en"},"user":{"screen_name":"paulwiggins","id_str":"10482452","id":10482452},"entities":{"user_mentions":[{"id_str":"30331417","screen_name":"evgenymorozov","indices":[3,17],"name":"Evgeny Morozov","id":30331417}],"hashtags":[],"urls":[{"url":"http://t.co/A1E6zLRz","display_url":"flpbd.it/D3jkI","indices":[93,113],"expanded_url":"http://flpbd.it/D3jkI"}]},"coordinates":null,"text":"RT @evgenymorozov: Religious Sites Carry More Malware Than Porn Sites, Security Firm Reports http://t.co/A1E6zLRz","created_at":"Mon, 30 Apr 2012 21:54:23 +0000","id_str":"197081489068916736","id":197081489068916740}
{"metadata":{"iso_language_code":"en"},"user":{"screen_name":"greylines101","id_str":"97091176","id":97091176},"entities":{"user_mentions":[{"id_str":"255947505","screen_name":"weemadjojo","indices":[0,11],"name":"joanne carson","id":255947505},{"id_str":"3819701","screen_name":"ZDNet","indices":[15,21],"name":"ZDNet","id":3819701}],"hashtags":[],"urls":[{"url":"http://t.co/1pG0ewVn","display_url":"zd.net/JWAlC3","indices":[108,128],"expanded_url":"http://zd.net/JWAlC3"}]},"coordinates":null,"text":"@weemadjojo RT @ZDNet: Spamvertised 'PayPal payment notifications' lead to client-side exploits and malware http://t.co/1pG0ewVn","created_at":"Thu, 03 May 2012 19:26:52 +0000","id_str":"198131531938676736","id":198131531938676740}
{"metadata":{"iso_language_code":"en"},"user":{"screen_name":"MaintainIT","id_str":"107152919","id":107152919},"entities":{"user_mentions":[],"hashtags":[],"urls":[]},"coordinates":null,"text":"Does your IT provider update you regularly on patch, OS, disk, event log, alarm, security, malware and server up time?  MaintainIT does.","created_at":"Tue, 01 May 2012 18:02:39 +0000","id_str":"197385558736109570","id":197385558736109570}
{"metadata":{"iso_language_code":"en"},"user":{"screen_name":"libfirebrand","id_str":"295783332","id":295783332},"entities":{"user_mentions":[{"id_str":"55355654","screen_name":"thinkprogress","indices":[120,134],"name":"ThinkProgress","id":55355654}],"hashtags":[],"urls":[{"url":"http://t.co/XQfIHtlU","display_url":"thkpr.gs/IPQFDl","indices":[95,115],"expanded_url":"http://thkpr.gs/IPQFDl"}]},"coordinates":null,"text":"Obama Defends Attack On Romney: ‘I Assumed’ He Meant It When He Said He Wouldn’t Get Bin Laden http://t.co/XQfIHtlU via @thinkprogress","created_at":"Tue, 01 May 2012 05:50:07 +0000","id_str":"197201211911454720","id":197201211911454720}
{"metadata":{"iso_language_code":"en"},"user":{"screen_name":"GooglePhones","id_str":"96661578","id":96661578},"entities":{"user_mentions":[],"hashtags":[{"indices":[88,100],"text":"GooglePhone"}],"urls":[{"url":"http://t.co/FGWvdfw0","display_url":"bit.ly/JBNgq6","indices":[67,87],"expanded_url":"http://bit.ly/JBNgq6"}]},"coordinates":null,"text":"Religious and ideological sites carry more malware than porn sites http://t.co/FGWvdfw0 #GooglePhone","created_at":"Tue, 01 May 2012 11:20:05 +0000","id_str":"197284250104504321","id":197284250104504320}
{"metadata":{"iso_language_code":"en"},"user":{"screen_name":"IanRush6","id_str":"523936657","id":523936657},"entities":{"user_mentions":[],"hashtags":[],"urls":[{"url":"http://t.co/Pj25xqoN","display_url":"tinyurl.com/7a5va6l","indices":[116,136],"expanded_url":"http://tinyurl.com/7a5va6l"}]},"coordinates":null,"text":"Mapping Security: A Network Analysis: The terrorist attack of 9/11 has created and/ oraccelerated increased pres... http://t.co/Pj25xqoN","created_at":"Sun, 29 Apr 2012 11:06:38 +0000","id_str":"196556088752095233","id":196556088752095230}
{"metadata":{"iso_language_code":"en"},"user":{"screen_name":"kingsoRSS","id_str":"544507459","id":544507459},"entities":{"user_mentions":[],"hashtags":[],"urls":[{"url":"http://t.co/CSWm5Ou9","display_url":"bit.ly/K4eG8m","indices":[116,136],"expanded_url":"http://bit.ly/K4eG8m"}]},"coordinates":null,"text":"Defence companies targeted in spear-phishing attack: A public-private sector information-sharing hub has reveale... http://t.co/CSWm5Ou9","created_at":"Thu, 03 May 2012 16:36:27 +0000","id_str":"198088642038738944","id":198088642038738940}
{"metadata":{"iso_language_code":"en"},"user":{"screen_name":"Solveris","id_str":"61892276","id":61892276},"entities":{"user_mentions":[{"id_str":"19254838","screen_name":"xbiz","indices":[3,8],"name":"XBIZ™","id":19254838}],"hashtags":[],"urls":[{"url":"http://t.co/M3hEHZbz","display_url":"bit.ly/IKdCEB","indices":[92,112],"expanded_url":"http://bit.ly/IKdCEB"}]},"coordinates":null,"text":"RT @xbiz: Study: Religious Sites Offer More Malware Than Porn Sites: security firm Symantec http://t.co/M3hEHZbz","created_at":"Mon, 30 Apr 2012 18:28:50 +0000","id_str":"197029762424770563","id":197029762424770560}
